__utils/__init__.py
__utils/funcs.py
ifeature/__init__.py
ifeature/eda/DataFrameSummary.py
ifeature/eda/__init__.py
ifeature/features_add/Binning.py
ifeature/features_add/CategoryFeature.py
ifeature/features_add/MissingFeature.py
ifeature/features_add/NumericalFeature.py
ifeature/features_add/RowFeature.py
ifeature/features_add/TimeFeature.py
ifeature/features_add/__init__.py
ifeature/features_sub/FeatureFilter.py
ifeature/features_sub/FeatureSelector.py
ifeature/features_sub/__init__.py
ifeature/features_sub/distcorr.py
ifeature/features_sub/info_value.py
ifeature/features_transform/__init__.py
ifeature/features_transform/encoder.py
ifeature/models/SemiSupervision.py
ifeature/models/__init__.py
ifeature/models/baseline.py
ifeature/models/eli5.py
ifeature/models/utils/__init__.py
ifeature/models/utils/_model_cv.py
ifeature/models/utils/get_class.py
ifeature/models/utils/online.py
ifeature/utils/DataCreate.py
ifeature/utils/Pickle.py
ifeature/utils/RemoveStopWords.py
ifeature/utils/__init__.py
ifeature/utils/auto_notebook.py
ifeature/utils/colors.py
ifeature/utils/decorator.py
ifeature/utils/file_processing.py
ifeature/utils/multi_func.py
ifeature/utils/os_utils.py
ifeature/utils/parallel.py
ifeature/utils/plot.py
ifeature/utils/reader_pandas.py
ifeature/utils/reader_parallel.py
ifeature/utils/shuffle_data.py
ifeature/utils/time_utils.py
ifeature-0.0.6.dist-info/METADATA
ifeature-0.0.6.dist-info/WHEEL
ifeature-0.0.6.dist-info/top_level.txt
ifeature-0.0.6.dist-info/RECORD
